{
  "name": "Mayme Abbott",
  "age": 19,
  "address": {
    "street": "Wasgu Extension",
    "city": "Jikwalu",
    "state": "DE",
    "zip": "85466"
  },
  "contact": {
    "phone": "(352) 816-9139",
    "servicePhone": "800842836"
  },
  "birthday": "1971-08-02T14:50:59.615Z",
  "ip": "24.183.122.214",
  "foo": "bar",
  "profile": {
    "about": "Savadki jinga ido va vatjivcos befkudlog sob dito bakfalka rela keamoto ovesinru mikgugib saljebo jowrah be. Ge suz loan bij hemriw buit fickim gal dobdi dozdatmu pej moj uzehen tome ewcu najlufiv udpohdib zi. Tek zu tescenbu fomev misohluh wukhowgob ek pa wal cizjelme upocbi dej omek ezirabon efu temzah puknoj mokmi. Pof desad lugbida ajra ko odzij ri ujipuzuh fim moc nokod ipavaju sutulu hofjogi vipwinuz re daw.",
    "bio": "Ucleco cuzekas gos fod luajifu nukgoczem co licepsof fupajhev igsev havhuvfud ajesiawa ze wubishif dupo bucim afevpir koppo. Ir kenihon konojse zejgev cahbet weluw sungo sabha tat zehe alzugoj eluwaru. Ba bo nufla ezojeve gornaote rugidofe zevunsa if kan gerja mo vacetav vut. Menger vu uz oneogofan rihozo did it su ces pulo las ma jedub pivtut feri. Is romlu ha umhop to jupze faged nag lod dodan kohobal vuloc ge. Suspiwra lo tizewi jo sedko jiplajowe fiwok fad wizev ucihuliv oh ekoze das cul. Hu alo sundezira keice red soduge taswomig fifagah ebuiwpev atipeknuw zodjewiv avur."
  },
  "apiKey": "1b514ede68e11a2a09c39eaf4436e4e2a3eedb57cce8b418c87cbc4d56013909",
  "currency": {
    "code": "AUD",
    "name": "Australia Dollar"
  }
}